Metadata-Version: 2.1
Name: pypydispatch
Version: 1.2.1
Summary: A library for event-driven programming, extracted from Django
Home-page: https://github.com/xiachufang/dispatcher
Maintainer: gfreezy
Maintainer-email: gfreezy@gmail.com
Classifier: Development Status :: 4 - Beta
Classifier: Operating System :: OS Independent
Classifier: Programming Language :: Python
Classifier: License :: OSI Approved :: BSD License
Classifier: Intended Audience :: Developers
Classifier: Topic :: Software Development :: Libraries :: Python Modules
